{
  "parent": "minecraft:recipes/root",
  "criteria": {
    "has_slice": {
      "conditions": {
        "items": [
          {
            "items": "brewinandchewin:pizza_slice"
          }
        ]
      },
      "trigger": "minecraft:inventory_changed"
    },
    "has_the_recipe": {
      "conditions": {
        "recipe": "brewinandchewin:pizza_from_slices"
      },
      "trigger": "minecraft:recipe_unlocked"
    }
  },
  "requirements": [
    [
      "has_the_recipe",
      "has_slice"
    ]
  ],
  "rewards": {
    "recipes": [
      "brewinandchewin:pizza_from_slices"
    ]
  }
}